outgoing_mailgun/__init__.py
outgoing_mailgun/py.typed
outgoing_mailgun-0.3.2.dist-info/METADATA
outgoing_mailgun-0.3.2.dist-info/WHEEL
outgoing_mailgun-0.3.2.dist-info/entry_points.txt
outgoing_mailgun-0.3.2.dist-info/licenses/LICENSE
outgoing_mailgun-0.3.2.dist-info/RECORD
