Metadata-Version: 2.4
Name: outgoing-mailgun
Version: 0.3.2
Summary: outgoing extension for Mailgun
Project-URL: Source Code, https://github.com/jwodder/outgoing-mailgun
Project-URL: Bug Tracker, https://github.com/jwodder/outgoing-mailgun/issues
Author-email: John Thorvald Wodder II <outgoing-mailgun@varonathe.org>
License-Expression: MIT
License-File: LICENSE
Keywords: Mailgun,e-mail,email,outgoing
Classifier: Intended Audience :: Developers
Classifier: Intended Audience :: Information Technology
Classifier: Intended Audience :: System Administrators
Classifier: License :: OSI Approved :: MIT License
Classifier: Programming Language :: Python :: 3
Classifier: Programming Language :: Python :: 3 :: Only
Classifier: Programming Language :: Python :: 3.8
Classifier: Programming Language :: Python :: 3.9
Classifier: Programming Language :: Python :: 3.10
Classifier: Programming Language :: Python :: 3.11
Classifier: Programming Language :: Python :: 3.12
Classifier: Programming Language :: Python :: 3.13
Classifier: Programming Language :: Python :: Implementation :: CPython
Classifier: Programming Language :: Python :: Implementation :: PyPy
Classifier: Topic :: Communications :: Email
Classifier: Typing :: Typed
Requires-Python: >=3.8
Requires-Dist: mailbits~=0.2
Requires-Dist: outgoing~=0.6
Requires-Dist: pydantic~=2.0
Requires-Dist: requests~=2.20
